pysim-2.4.0.dist-info/METADATA
pysim-2.4.0.dist-info/LICENSE.txt
pysim-2.4.0.dist-info/RECORD
pysim-2.4.0.dist-info/WHEEL
pysim-2.4.0.dist-info/top_level.txt
pysim-2.4.0.data/scripts/new_pysim_system.py
pysim/info.py
pysim/__init__.py
pysim/commonsystem.cpython-39-x86_64-linux-gnu.so
pysim/simulatablesystem.pxd
pysim/cppsystem.cpython-39-x86_64-linux-gnu.so
pysim/simulation.cpython-39-x86_64-linux-gnu.so
pysim/simulatablesystem.cpython-39-x86_64-linux-gnu.so
pysim/cppsystem.pxd
pysim/compositesystem.pxd
pysim/connections.pxd
pysim/cythonsystem.cpython-39-x86_64-linux-gnu.so
pysim/compositesystem.cpython-39-x86_64-linux-gnu.so
pysim/connections.cpython-39-x86_64-linux-gnu.so
pysim/commonsystem.pxd
pysim/cythonsystem.pxd
pysim/systems/python_systems.py
pysim/systems/__init__.py
pysim/systems/defaultsystemcollection1.cpython-39-x86_64-linux-gnu.so
pysim/tests/store_test.py
pysim/tests/parameter_test.py
pysim/tests/system_readtextinput_test.py
pysim/tests/__init__.py
pysim/tests/compositesystem_test.py
pysim/tests/state_test.py
pysim/tests/poststep_test.py
pysim/tests/integration_test.py
pysim/tests/input_ouput_test.py
pysim/tests/prestep_test.py
pysim/tests/configfile_test.py
pysim/tests/cppsystem_test.py
pysim/tests/simulation_test.py
pysim/lib/libcppsystemlib.a
pysim/include/CppSystem.hpp
pysim/include/CythonSystemImpl.hpp
pysim/include/ConnectionHandler.hpp
pysim/include/StoreHandler.hpp
pysim/include/Variable.hpp
pysim/include/CompositeSystemImpl.hpp
pysim/include/CommonSystemImpl.hpp
pysim/include/SimulatableSystem.hpp
pysim/include/PysimTypes.hpp
pysim/templates/system_template.hpp
pysim/templates/system_template.cpp
